sciviewer/__init__.py
sciviewer/gui.py
sciviewer/sciviewer.py
sciviewer/utils.py
sciviewer-0.13.dist-info/LICENSE
sciviewer-0.13.dist-info/METADATA
sciviewer-0.13.dist-info/WHEEL
sciviewer-0.13.dist-info/top_level.txt
sciviewer-0.13.dist-info/RECORD
