Metadata-Version: 2.1
Name: sciviewer
Version: 0.13
Summary: Tool for interactive exploration of 2D embeddings in Jupyter
Home-page: https://github.com/colabobio/sciviewer
Author: Andres Colubri, Dylan Kotliar
Author-email: andres@broadinstitute.org, dylan_kotliar@hms.harvard.edu
License: MIT
Platform: UNKNOWN
License-File: LICENSE
Requires-Dist: py5
